neopolitan/HowOperationsWork.md
neopolitan/ReadMe.md
neopolitan/__init__.py
neopolitan/const.py
neopolitan/demos.py
neopolitan/log.py
neopolitan/naples.py
neopolitan/neop.py
neopolitan/nonblocking.py
neopolitan/os_detection.py
neopolitan/testboardrunner.py
neopolitan/board_functions/__init__.py
neopolitan/board_functions/board.py
neopolitan/board_functions/board_data.py
neopolitan/board_functions/colors.py
neopolitan/display/__init__.py
neopolitan/display/abstract_board_display.py
neopolitan/display/abstract_display.py
neopolitan/display/graphical_board_display.py
neopolitan/display/graphical_display.py
neopolitan/display/hardware_board_display.py
neopolitan/display/hardware_display.py
neopolitan/writing/ReadMe.md
neopolitan/writing/__init__.py
neopolitan/writing/data_transformation.py
neopolitan/writing/groups_8.py
neopolitan/writing/letters_8.py
neopolitan-0.1.41.dist-info/METADATA
neopolitan-0.1.41.dist-info/WHEEL
neopolitan-0.1.41.dist-info/licenses/LICENSE
neopolitan-0.1.41.dist-info/RECORD
