Metadata-Version: 2.1
Name: neopolitan
Version: 0.1.41
Summary: Neopolitan: a library for displaying text on LED boards
Project-URL: Homepage, https://github.com/alyoshenka/neopolitan
Author: alyo
License-File: LICENSE
Classifier: License :: OSI Approved :: MIT License
Classifier: Operating System :: OS Independent
Classifier: Programming Language :: Python :: 3
Requires-Python: >=3.7
Requires-Dist: adafruit-circuitpython-neopixel; platform_machine == 'aarch64'
Requires-Dist: adafruit-circuitpython-neopixel; platform_machine == 'armv7l'
Requires-Dist: pygame; platform_machine == 'x86_64'
Requires-Dist: rpi-gpio; platform_machine == 'aarch64'
Requires-Dist: rpi-gpio; platform_machine == 'armv7l'
Requires-Dist: rpi-ws281x; platform_machine == 'aarch64'
Requires-Dist: rpi-ws281x; platform_machine == 'armv7l'
